cml_mcp/__init__.py
cml_mcp/__main__.py
cml_mcp/cml_client.py
cml_mcp/py.typed
cml_mcp/server.py
cml_mcp/settings.py
cml_mcp/types.py
cml_mcp/cml/simple_common/__init__.py
cml_mcp/cml/simple_common/schemas.py
cml_mcp/cml/simple_webserver/__init__.py
cml_mcp/cml/simple_webserver/schemas/__init__.py
cml_mcp/cml/simple_webserver/schemas/ai.py
cml_mcp/cml/simple_webserver/schemas/annotations.py
cml_mcp/cml/simple_webserver/schemas/authentication.py
cml_mcp/cml/simple_webserver/schemas/common.py
cml_mcp/cml/simple_webserver/schemas/diagnostics.py
cml_mcp/cml/simple_webserver/schemas/external_connector.py
cml_mcp/cml/simple_webserver/schemas/groups.py
cml_mcp/cml/simple_webserver/schemas/image_definitions.py
cml_mcp/cml/simple_webserver/schemas/imports.py
cml_mcp/cml/simple_webserver/schemas/int_compute.py
cml_mcp/cml/simple_webserver/schemas/interfaces.py
cml_mcp/cml/simple_webserver/schemas/internals.py
cml_mcp/cml/simple_webserver/schemas/keys.py
cml_mcp/cml/simple_webserver/schemas/labs.py
cml_mcp/cml/simple_webserver/schemas/licensing.py
cml_mcp/cml/simple_webserver/schemas/licensing_reservation.py
cml_mcp/cml/simple_webserver/schemas/links.py
cml_mcp/cml/simple_webserver/schemas/network_addresses.py
cml_mcp/cml/simple_webserver/schemas/node_definitions.py
cml_mcp/cml/simple_webserver/schemas/nodes.py
cml_mcp/cml/simple_webserver/schemas/parameters.py
cml_mcp/cml/simple_webserver/schemas/pcap.py
cml_mcp/cml/simple_webserver/schemas/pyats.py
cml_mcp/cml/simple_webserver/schemas/resource_pools.py
cml_mcp/cml/simple_webserver/schemas/responses.py
cml_mcp/cml/simple_webserver/schemas/sample_labs.py
cml_mcp/cml/simple_webserver/schemas/smart_annotations.py
cml_mcp/cml/simple_webserver/schemas/system.py
cml_mcp/cml/simple_webserver/schemas/telemetry.py
cml_mcp/cml/simple_webserver/schemas/topologies.py
cml_mcp/cml/simple_webserver/schemas/ui_helpers.py
cml_mcp/cml/simple_webserver/schemas/users.py
cml_mcp/cml/simple_webserver/schemas/web_sockets.py
iflow_mcp_xorrkaz_cml-0.21.3.dist-info/licenses/CISCO_LICENSE.md
iflow_mcp_xorrkaz_cml-0.21.3.dist-info/licenses/LICENSE
iflow_mcp_xorrkaz_cml-0.21.3.dist-info/METADATA
iflow_mcp_xorrkaz_cml-0.21.3.dist-info/WHEEL
iflow_mcp_xorrkaz_cml-0.21.3.dist-info/entry_points.txt
iflow_mcp_xorrkaz_cml-0.21.3.dist-info/top_level.txt
iflow_mcp_xorrkaz_cml-0.21.3.dist-info/RECORD
