Metadata-Version: 2.4
Name: iflow-mcp-xorrkaz-cml
Version: 0.21.3
Summary: Cisco Modeling Labs (CML) MCP Server
Author-email: Joe Clarke <jclarke@cisco.com>
License-Expression: BSD-2-Clause AND LicenseRef-Proprietary
Project-URL: Homepage, https://github.com/xorrkaz/cml-mcp
Project-URL: Issues, https://github.com/xorrkaz/cml-mcp/issues
Classifier: Programming Language :: Python :: 3
Classifier: Operating System :: OS Independent
Requires-Python: <4.0,>=3.11
License-File: LICENSE
License-File: CISCO_LICENSE.md
Requires-Dist: httpx
Requires-Dist: fastmcp>=2.13.1
Requires-Dist: fastapi
Requires-Dist: pydantic_strict_partial
Requires-Dist: typer
Requires-Dist: virl2_client
Provides-Extra: pyats
Requires-Dist: pyats; extra == "pyats"
Requires-Dist: genie; extra == "pyats"
Dynamic: license-file
